maldump-0.5.0.dist-info/METADATA
maldump-0.5.0.dist-info/WHEEL
maldump-0.5.0.dist-info/entry_points.txt
maldump-0.5.0.dist-info/licenses/LICENSE
maldump/__init__.py
maldump/__main__.py
maldump/av_manager.py
maldump/avs/__init__.py
maldump/avs/avast.py
maldump/avs/avg.py
maldump/avs/avira.py
maldump/avs/eset.py
maldump/avs/forticlient.py
maldump/avs/gdata.py
maldump/avs/kaspersky.py
maldump/avs/malwarebytes.py
maldump/avs/mcafee.py
maldump/avs/windef.py
maldump/parsers/__init__.py
maldump/parsers/avast_parser.py
maldump/parsers/avg_parser.py
maldump/parsers/avira_parser.py
maldump/parsers/eset_parser.py
maldump/parsers/forticlient_parser.py
maldump/parsers/gdata_parser.py
maldump/parsers/kaitai/__init__.py
maldump/parsers/kaitai/avira_parser.ksy
maldump/parsers/kaitai/avira_parser.py
maldump/parsers/kaitai/forticlient_parser.ksy
maldump/parsers/kaitai/forticlient_parser.py
maldump/parsers/kaitai/gdata_parser.ksy
maldump/parsers/kaitai/gdata_parser.py
maldump/parsers/kaitai/windef_entries.ksy
maldump/parsers/kaitai/windef_entries.py
maldump/parsers/kaitai/windef_resource_data.ksy
maldump/parsers/kaitai/windef_resource_data.py
maldump/parsers/kaspersky_parser.py
maldump/parsers/malwarebytes_parser.py
maldump/parsers/mcafee_parser.py
maldump/parsers/windef_parser.py
maldump/structures.py
maldump/utils.py
test/__init__.py
test/root/$AV_ASW/$VAULT/vault.db
test/root/$AV_AVG/$VAULT/vault.db
test/root/Program Files/Fortinet/FortiClient/quarantine/QuarantFile29503db7_2172
test/root/ProgramData/AVG/Antivirus/chest/index.xml
test/root/ProgramData/Avast Software/Avast/chest/index.xml
test/root/ProgramData/Avira/Antivirus/INFECTED/7372ec3d.qua
test/root/ProgramData/ESET/ESET Security/Logs/virlog.dat
test/root/ProgramData/G Data/AVK/Quarantine/180122064819413FA3B80.q
test/root/ProgramData/Kaspersky Lab/Kaspersky Security for Windows Server/11.0/Quarantine/quarantine.db
test/root/ProgramData/Kaspersky Lab/Kaspersky Security for Windows Server/11.0/Quarantine/{98571591-f30d-453e-b6ed-6ff2cf218344}
test/root/ProgramData/Malwarebytes/MBAMService/Quarantine/bcd0b1ad-04d1-11ec-92be-080027e6e559.data
maldump-0.5.0.dist-info/RECORD
