Metadata-Version: 2.1
Name: maldump
Version: 0.5.0
Summary: Multi-quarantine extractor
Author: Erik Kuna, Jež Dominik, Jonáš Novotný, Nikola Knežević
License: GPLv3
Classifier: License :: OSI Approved :: GNU General Public License v3 (GPLv3)
Classifier: Operating System :: OS Independent
Classifier: Programming Language :: Python :: 3
Classifier: Topic :: Security
Project-URL: Homepage, https://github.com/NUKIB/maldump
Project-URL: Bug tracker, https://github.com/NUKIB/maldump/issues
Requires-Python: >=3.8
Requires-Dist: colorama==0.4.6
Requires-Dist: defusedxml==0.7.1
Requires-Dist: kaitaistruct==0.10
Requires-Dist: arc4==0.4.0
Requires-Dist: types-colorama==0.4.15.12
